AUTHORS.rst
LICENSE
MANIFEST.in
README.md
setup.py
climetlab_eumetnet_postprocessing_benchmark/__init__.py
climetlab_eumetnet_postprocessing_benchmark/config.py
climetlab_eumetnet_postprocessing_benchmark/utils.py
climetlab_eumetnet_postprocessing_benchmark/version
climetlab_eumetnet_postprocessing_benchmark.egg-info/PKG-INFO
climetlab_eumetnet_postprocessing_benchmark.egg-info/SOURCES.txt
climetlab_eumetnet_postprocessing_benchmark.egg-info/dependency_links.txt
climetlab_eumetnet_postprocessing_benchmark.egg-info/entry_points.txt
climetlab_eumetnet_postprocessing_benchmark.egg-info/requires.txt
climetlab_eumetnet_postprocessing_benchmark.egg-info/top_level.txt
climetlab_eumetnet_postprocessing_benchmark.egg-info/zip-safe
climetlab_eumetnet_postprocessing_benchmark/EUPP/__init__.py
climetlab_eumetnet_postprocessing_benchmark/EUPP/gridded/__init__.py
climetlab_eumetnet_postprocessing_benchmark/EUPP/gridded/static_fields_data.py
climetlab_eumetnet_postprocessing_benchmark/EUPP/gridded/training_data_forecasts.py
climetlab_eumetnet_postprocessing_benchmark/EUPP/gridded/training_data_reforecasts.py
climetlab_eumetnet_postprocessing_benchmark/EUPP/stations/__init__.py
climetlab_eumetnet_postprocessing_benchmark/EUPP/stations/training_data_forecasts.py
climetlab_eumetnet_postprocessing_benchmark/EUPP/stations/training_data_reforecasts.py
climetlab_eumetnet_postprocessing_benchmark/EUPreciP/__init__.py
climetlab_eumetnet_postprocessing_benchmark/EUPreciP/precipitations.py
climetlab_eumetnet_postprocessing_benchmark/gridded/__init__.py
climetlab_eumetnet_postprocessing_benchmark/gridded/static_fields_data.py
climetlab_eumetnet_postprocessing_benchmark/gridded/training_data_forecasts.py
climetlab_eumetnet_postprocessing_benchmark/gridded/training_data_reforecasts.py
docs/Makefile
docs/make.bat
docs/build/html/_images/gridded_data.jpg
docs/build/html/_images/gridded_data_EUPP.jpg
docs/build/html/_images/stations_data_EUPP.jpg
docs/build/html/_static/file.png
docs/build/html/_static/logo-eumetnet.png
docs/build/html/_static/minus.png
docs/build/html/_static/plus.png
docs/source/conf.py
docs/source/index.rst
docs/source/files/EUPPBench_datasets.rst
docs/source/files/base_datasets.rst
docs/source/files/datasets_status.rst
docs/source/images/gridded_data.jpg
docs/source/images/gridded_data_EUPP.jpg
docs/source/images/logo-eumetnet.png
docs/source/images/stations_data_EUPP.jpg
tests/test_notebooks.py
tests/test_training_data_forecasts.py
