Metadata-Version: 2.1
Name: climetlab-eumetnet-postprocessing-benchmark
Version: 0.3.3
Summary: A plugin for climetlab to retrieve the EUMETNET postprocessing benchmark dataset.
Home-page: https://github.com/Climdyn/climetlab-eumetnet-postprocessing-benchmark
Author: Jonathan Demaeyer
Author-email: jodemaey@meteo.be
License: BSD-3-Clause License
Keywords: meteorology,meteorological-data,postprocessing
Classifier: Development Status :: 5 - Production/Stable
Classifier: Intended Audience :: Science/Research
Classifier: License :: OSI Approved :: BSD License
Classifier: Programming Language :: Python :: 3
Classifier: Programming Language :: Python :: 3.9
Classifier: Programming Language :: Python :: 3.10
Classifier: Programming Language :: Python :: Implementation :: CPython
Classifier: Programming Language :: Python :: Implementation :: PyPy
Classifier: Operating System :: OS Independent
License-File: LICENSE
License-File: AUTHORS.rst
